apn_dot2tex/__init__.py
apn_dot2tex/dot2tex.py
apn_dot2tex/dotparsing.py
apn_dot2tex-2.15.0.data/scripts/dot2tex
apn_dot2tex-2.15.0.dist-info/licenses/AUTHORS
apn_dot2tex-2.15.0.dist-info/licenses/LICENSE
apn_dot2tex-2.15.0.dist-info/METADATA
apn_dot2tex-2.15.0.dist-info/WHEEL
apn_dot2tex-2.15.0.dist-info/entry_points.txt
apn_dot2tex-2.15.0.dist-info/top_level.txt
apn_dot2tex-2.15.0.dist-info/RECORD
